yta_image_masking/__init__.py
yta_image_masking/greenscreen/__init__.py
yta_image_masking/greenscreen/dataclasses.py
yta_image_masking/greenscreen/threed.py
yta_image_masking/greenscreen/utils.py
yta_image_masking-0.0.3.dist-info/LICENSE
yta_image_masking-0.0.3.dist-info/METADATA
yta_image_masking-0.0.3.dist-info/WHEEL
yta_image_masking-0.0.3.dist-info/RECORD
