Metadata-Version: 2.3
Name: yta-image-masking
Version: 0.0.3
Summary: Youtube Autonomous Image Utils Module.
Author: danialcala94
Author-email: danielalcalavalera@gmail.com
Requires-Python: ==3.9
Classifier: Programming Language :: Python :: 3
Classifier: Programming Language :: Python :: 3.9
Requires-Dist: numpy (>=0.0.1,<9.0.0)
Requires-Dist: opencv-python (>=0.0.1,<9.0.0)
Requires-Dist: pillow (>=0.0.1,<19.0.0)
Requires-Dist: yta_colors (>=0.0.1,<1.0.0)
Requires-Dist: yta_constants (>=0.0.1,<1.0.0)
Requires-Dist: yta_image_base (>=0.0.1,<1.0.0)
Requires-Dist: yta_validation (>=0.0.1,<1.0.0)
